sedparse.py
sedparse-0.1.2.dist-info/LICENSE
sedparse-0.1.2.dist-info/METADATA
sedparse-0.1.2.dist-info/WHEEL
sedparse-0.1.2.dist-info/entry_points.txt
sedparse-0.1.2.dist-info/top_level.txt
sedparse-0.1.2.dist-info/RECORD
