Metadata-Version: 2.1
Name: sedparse
Version: 0.1.2
Summary: GNU sed's parser translated from C to Python
Home-page: https://github.com/aureliojargas/sedparse
Author: Aurelio Jargas
Author-email: aurelio@aurelio.net
License: UNKNOWN
Project-URL: Bug Tracker, https://github.com/aureliojargas/sedparse/issues
Project-URL: Source Code, https://github.com/aureliojargas/sedparse
Platform: UNKNOWN
Classifier: Development Status :: 4 - Beta
Classifier: Environment :: Console
Classifier: Intended Audience :: Developers
Classifier: License :: OSI Approved :: GNU General Public License v3 (GPLv3)
Classifier: Operating System :: OS Independent
Classifier: Programming Language :: Python :: 2
Classifier: Programming Language :: Python :: 2.7
Classifier: Programming Language :: Python :: 3
Classifier: Programming Language :: Python :: 3.4
Classifier: Programming Language :: Python :: 3.5
Classifier: Programming Language :: Python :: 3.6
Classifier: Programming Language :: Python :: 3.7
Classifier: Programming Language :: Python :: 3.8
Classifier: Programming Language :: Python
Classifier: Topic :: Software Development
Requires-Python: >=2.7, !=3.0.*, !=3.1.*, !=3.2.*, !=3.3.*
